MANIFEST.in
README.md
setup.py
finwizard/__init__.py
finwizard/budget.py
finwizard.egg-info/PKG-INFO
finwizard.egg-info/SOURCES.txt
finwizard.egg-info/dependency_links.txt
finwizard.egg-info/not-zip-safe
finwizard.egg-info/requires.txt
finwizard.egg-info/top_level.txt