Metadata-Version: 1.0
Name: finwizard
Version: 0.1
Summary: This package is a personal finance tool.
Home-page: http://gitlab.com/porterjs/finwizard
Author: JEBBS
Author-email: jasonsporter88@gmail.com
License: JSP
Keywords: finwizard personal finance plan budget
Platform: UNKNOWN
